README
pyxdebug.py
setup.py
pyxdebug.egg-info/PKG-INFO
pyxdebug.egg-info/SOURCES.txt
pyxdebug.egg-info/dependency_links.txt
pyxdebug.egg-info/top_level.txt