Metadata-Version: 1.0
Name: pyxdebug
Version: 1.2.2
Summary: PyXdebug is Xdebug format debugger for Python
Home-page: http://github.com/eth0jp/python-xdebug
Author: Yoshida Tetsuya
Author-email: tetu@eth0.jp
License: MIT License
Keywords: xdebug profile profiler
Platform: UNKNOWN
Classifier: Development Status :: 5 - Production/Stable
Classifier: Intended Audience :: Developers
Classifier: License :: OSI Approved :: MIT License
Classifier: Operating System :: POSIX
Classifier: Operating System :: MacOS
Classifier: Programming Language :: Python
Classifier: Programming Language :: PHP
Classifier: Topic :: Software Development :: Debuggers
Classifier: Topic :: Software Development :: Libraries :: Python Modules
